{
    "langcode": "es",
    "calendarLangData": {
        "dateformat": "%m.%d.%Y",
        "monthesFNames": [
            "Enero",
            "Febrero",
            "Marzo",
            "Abril",
            "Mayo",
            "Junio",
            "Julio",
            "Agosto",
            "Septiembre",
            "Octubre",
            "Noviembre",
            "Diciembre"
        ],
        "monthesSNames": [
            "ene",
            "feb",
            "mar",
            "abr",
            "may",
            "jun",
            "jul",
            "ago",
            "sep",
            "oct",
            "nov",
            "dic"
        ],
        "daysFNames": [
            "domingo",
            "lunes",
            "martes",
            "miércoles",
            "jueves",
            "viernes",
            "sábado"
        ],
        "daysSNames": [
            "do",
            "lu",
            "ma",
            "mié",
            "jue",
            "vie",
            "sáb"
        ],
        "weekstart": "0",
        "weekname": "s",
        "today": "Hoy",
        "clear": "Borrar"
    },
    "Vintuoso": "Vintuoso",
    "Hello": "Hola",
    "SaveSettings": "Guardar ajustes",
    "Save": "Guardar",
    "Delete": "Borrar",
    "Edit": "Editar",
    "Share": "Compartir",
    "Generate": "Imprimir",
    "SignIn": "Registrarse",
    "SignOut": "Desconectarse",
    "YouWillBeSignedOut": "serás desconectado",
    "SignUp": "Inscribirse",
    "SearchAddress": "Buscar dirección",
    "Title": "Título",
    "Unknown": "Desconocido",
    "Price": "Precio",
    "Venue": "Sede",
    "Address": "Habla a",
    "Dates": "fechas",
    "Time": "Hora",
    "Styles": "Estilos",
    "Type": "Tipo",
    "NewUser": "Nuevo usuario(a)",
    "Username": "Nombre de usuario(a)",
    "Password": "Contraseña",
    "NewPassword": "Nueva contraseña",
    "Email": "Correo electrónico",
    "Saving": "Guardando...",
    "SavingWine": "Guardando vino...",
    "CommunicationWithTheServer": "La comunicación con el servidor está en curso...",
    "Loading": "Cargando datos...",
    "Deleting": "Borrando...",
    "UserSettings": "Ajustes de usuario(a)",
    "UserSettingsSaved": "Configuración de usuario(a) guardada",
    "UserSettingsNotSaved": "No se puede guardar la configuración del usuario(a)",
    "Sugar": "Azúcar",
    "Salt": "Sal",
    "Fat": "Grasa",
    "Spiciness": "Picante",
    "Acidity": "Acidez",
    "Astringency": "Astringencia",
    "Tannins": "taninos",
    "Body": "Cuerpo",
    "Bitterness": "Amargura",
    "Persistence": "Persistencia",
    "Complexity": "Complejidad",
    "Gas": "Gas",
    "Description": "Descripción",
    "Label": "Etiqueta",
    "Visual": "Visual",
    "Olfaction": "Olfato",
    "Taste": "Gusto",
    "Conclusion": "Conclusión",
    "Name": "Nombre",
    "TastingDate": "Fecha de cata",
    "Vintage": "Añada",
    "Alcohol": "Alcohol",
    "Organic": "Orgánico",
    "Sulfites": "Sulfitos",
    "Appellation": "Denominación",
    "Producer": "Productor",
    "Boutique": "Bodega",
    "Varieties": "Variedades",
    "Intensity": "Intensidad aromática",
    "PickAromas": "Elige aromas",
    "BackToWineEdit": "Volver a editar vino",
    "Aromas": "Aromas",
    "Comments": "Comentarios",
    "ShowHideSelectedAromas": "mostrar/ocultar aromas seleccionados",
    "ShowHideFilters": "mostrar/ocultar filtros",
    "TapToSelectAromas": "Toca para seleccionar aromas",
    "TapToSelectFood": "Toca para seleccionar la comida",
    "AcidityFlat": "Departamento",
    "AcidityNone": "Ninguna",
    "AcidityLow": "Bajo",
    "AcidityMedium": "Medio",
    "AcidityHigh": "Alta acidez",
    "AcidityFresh": "Fresco",
    "AcidityAcid": "Ácido",
    "AstringencyNone": "Ninguna",
    "AstringencyLow": "Bajo",
    "AstringencyMedium": "Medio",
    "AstringencyTannic": "Tánico",
    "AstringencyRough": "Áspero",
    "IntensityLow": "Baja",
    "IntensityMediumLow": "Medio-baja",
    "IntensityMedium": "Media",
    "IntensityMediumHigh": "Medio-alta",
    "IntensityHigh": "Alta",
    "FatNone": "Ninguna",
    "FatLow": "Baja",
    "FatMedium": "Media",
    "FatFat": "Grasa",
    "BodyFluid": "Fluido",
    "BodyLight": "Luz",
    "BodyMedium": "Medio",
    "BodyFull": "Completo",
    "BodyHeavy": "Pesado",
    "PersistenceNone": "Ninguna",
    "PersistenceShort": "Pequeño",
    "PersistenceMedium": "Medio",
    "PersistenceLong": "Largo",
    "PersistenceExtra": "Extra",
    "TanninsNone": "Ninguna",
    "TanninsLight": "Legero",
    "TanninsSmooth": "Suave",
    "TanninsDry": "Seco",
    "TanninsHarsh": "Duro",
    "TransparencyTransparent": "Transparente",
    "TransparencyTinted": "Teñido",
    "TransparencyMedium": "Medio",
    "TransparencyHue": "Matiz",
    "TransparencyOpaque": "Opaco",
    "SugarExtraBrut": "Extrabruto",
    "SugarBrut": "Bruto",
    "SugarDry": "Seco",
    "SugarNone": "Sin azucar",
    "SugarLow": "Bajo nivel de azúcar",
    "SugarSemiDry": "Semi seco",
    "SugarSweet": "Dulce",
    "SugarVerySweet": "Muy dulce",
    "SugarLiquor": "Crema",
    "SpicinessNone": "Ninguna",
    "SpicinessLow": "Un poco",
    "SpicinessSpicy": "Picante",
    "SpicinessHot": "Caliente",
    "SaltNone": "Ninguna",
    "SaltSalty": "Salado",
    "SaltVerySalty": "Salado",
    "SaltMineral": "Mineral",
    "SaltSaline": "Salino",
    "ParticlesLimpid": "Límpido",
    "ParticlesPresent": "Deposición",
    "ParticlesCloudy": "Turbio",
    "GasStill": "Sin gas",
    "GasBeady": "Poco espumante",
    "GasSemiSparkling": "Espumante",
    "GasSparkling": "Espumoso",
    "BitternessNone": "Ninguna",
    "BitternessBitterish": "Amargura",
    "BitternessBitter": "Amargo",
    "BioNo": "No",
    "BioOrganic": "Orgánico",
    "BioBiodynamic": "Biodinámico",
    "BioEnvironment": "Favorable al medio ambiente",
    "SulfitesYes": "Sulfitos añadidos",
    "SulfitesNo": "Sin sulfitos añadidos",
    "WineNotSaved": "No se puede guardar el vino",
    "WineSaved": "Tu vino ha sido guardado",
    "FoodNotSaved": "No se puede guardar tu publicación de comida",
    "FoodSaved": "Tu publicación de comida ha sido guardada",
    "WineDeleted": "Tu vino ha sido eliminado.",
    "IncompleteInformation": "Información incompleta",
    "EmptyWineName": "Nombre de vino vacío",
    "EmptyWineLabel": "No se proporciona etiqueta",
    "EmptyFoodImage": "No se proporcionó imagen",
    "EmptyVintage": "Vendimia vacía",
    "EmptyTastingDate": "Fecha de cata vacía",
    "EmptyAlcohol": "Tasa de alcohol en vacío",
    "EmptyAppellation": "Falta la denominación",
    "AppellationWillBeCreated": "(denominación) será creada",
    "EmptyProducer": "Falta el productor",
    "ProducerWillBeCreated": "(productor) será creado",
    "EmptyBoutique": "Falta la bodega",
    "BoutiqueWillBeCreated": "(bodega) será creado",
    "EmptyVarieties": "Falta la lista de variedades",
    "EmptyAromas": "Falta la lista de aromas",
    "EmptyWines": "Falta la lista de vinos",
    "Wines": "Vinos",
    "Tags": "Etiquetas",
    "EmptyTags": "No se han seleccionado etiquetas de alimentos",
    "EmptyIntensity": "Intensidad indefinida",
    "EmptyColor": "Color indefinido",
    "Color": "Color",
    "Theme": "Tema",
    "NodeAskPermission": "Pida convertirse en moderador o informe de un problema",
    "WillBeDeleted": "será borrado!",
    "Ok": "OK",
    "Confirm": "Confirmar",
    "Cancel": "Cancelar",
    "UserNotFound": "contraseña no encontrada o incorrecta",
    "UseTaken": "nombre de usuario ya tomado",
    "MailTaken": "dirección ya tomada",
    "PasswordReset": "restablecer la contraseña",
    "UnableToConnect": "No es posible conectarse al servidor",
    "GeolocationFailed": "Error de geolocalización",
    "GeolocationDisabled": "La geolocalización está deshabilitada",
    "DefineAsDefaultLocation": "Haga clic aquí para definir esta ubicación por defecto",
    "Today": "Hoy dia",
    "LoginToPostMessages": "Por favor, inicie sesión o regístrese para publicar mensajes. Se tarda menos de un minuto",
    "UnableToPostMessages": "No se pudo publicar su mensaje, <br> verifique su red",
    "CommentViolation": "Tu comentario viola nuestras políticas.",
    "ServerGetResultsError": "No se pudo conectar al servidor, <br> por favor, vuelva a intentarlo más tarde",
    "UploadTimeout": "La carga de la imagen tomó demasiado tiempo, verifique el estado de su red e intente nuevamente",
    "UploadError": "La carga de la imagen falló, verifique el estado de su red e intente nuevamente",
    "FromDate": "Desde",
    "TillDate": "hasta",
    "InvalidDates": "Formato de fechas inválido",
    "InvalidPlace": "Lugar inválido",
    "GettingUserPosition": "Inicializando mapa",
    "PermissionsNeeded": "Permisos necesarios",
    "MapPermission": "Permita el acceso a la ubicación para mostrar las tiendas de vinos cercanas",
    "TranslationQuotaExceeded": "Lo sentimos, su cuota de traducción <br> por día excedió",
    "OneMoment": "Configurando la aplicación, por favor espere...",
    "Connecting": "Conectando...",
    "YouAreOffline": "Estas desconectado",
    "InitializationError": "No se pudo inicializar la aplicación<br>Por favor, verifique su conexión a Internet<br>O vuelva a intentarlo más tarde",
    "AccessLocation": "Permitir ubicación",
    "GoToSettings": "Ve a la configuración de tu teléfono",
    "AllowLocation": "Permitir que la ubicación muestre vinos a tu alrededor",
    "ShowFullArticle": "Mostrar artículo completo",
    "SearchResults": "Resultados de búsqueda de",
    "SearchOnline": "Buscar en línea",
    "SearchMoreOnline": "Buscar más en línea",
    "NoRecordsFound": "No se encontraron registros",
    "YouWillBeLoggedOut": "Será desconectado(a)",
    "Poor": "Málo",
    "Mediocre": "Mediocre",
    "Average": "Promedio",
    "Good": "Bien",
    "Excellent": "Excelente",
    "YouVoted": "Votado(a)",
    "Level": "Nivel",
    "Votes": "Votos",
    "PleaseRateUsTitle": "¡Califica la aplicación!",
    "PleaseRateUsContent": "Este servicio es completamente gratuito y tiene anuncios, pero lleva mucho tiempo y esfuerzo traerlo a usted. Por favor, califique la aplicación en la tienda",
    "AlreadyDone": "¡Ya hecho!",
    "ThankYou": "¡Gracias!",
    "UploadingLabel": "Subiendo etiqueta..",
    "UploadingImage": "Subiendo imagen..",
    "Done": "¡Hecho!",
    "Skip": "Saltar",
    "About": "Sobre",
    "Welcome": "¡Bienvenido a Vintuoso!",
    "MyCellar": "Mi bodega",
    "Access": "Acceso",
    "Navigation": "Navegación",
    "SearchFor": "Buscar",
    "FoodPairing": "Maridaje",
    "Profile": "Perfil",
    "Natural": "Natural",
    "OnlyNaturalWines": "Solo vinos naturales",
    "OnlyBioWines": "Solo vinos ecológicos",
    "OnlyVeganWines": "Solo vinos veganos",
    "Vegan": "Vegano",
    "VeganNo": "No vegano",
    "VeganYes": "Vegano",
    "Stock": "Existencias",
    "OpenANewBottle": "Abre una nueva botella",
    "PostAComment": "Publicar un comentario",
    "Post": "Correo",
    "DarkMode": "Modo oscuro",
    "NotABottle": "La foto no es una botella de vino, proporciona otra foto",
    "ExplicitContent": "¡Contenido explícito detectado!",
    "ProcessingImage": " Procesando imagen, por favor espere..."
}