{
    "langcode": "ru",
    "calendarLangData": {
        "dateformat": "%m.%d.%Y",
        "monthesFNames": [
            "Январь",
            "Февраль",
            "Март",
            "Апрель",
            "Май",
            "Июнь",
            "Июль",
            "Август",
            "Сентябрь",
            "Октябрь",
            "Ноябрь",
            "Декабрь"
        ],
        "monthesSNames": [
            "Янв",
            "Фев",
            "Мар",
            "Апр",
            "Май",
            "Июн",
            "Июл",
            "Авг",
            "Сен",
            "Окт",
            "Ноя",
            "Дек"
        ],
        "daysFNames": [
            "Воскресенье",
            "Понедельник",
            "Вторник",
            "Среда",
            "Четверг",
            "Пятница",
            "Суббота"
        ],
        "daysSNames": [
            "Су",
            "Мо",
            "Ту",
            "Мы",
            "Чт",
            "Пт",
            "Сб"
        ],
        "weekstart": "0",
        "weekname": "н",
        "today": "Сегодня",
        "clear": "Очистить"
    },
    "Vintuoso": "Винтуозо",
    "Hello": "Привет",
    "SaveSettings": "Сохранить настройки",
    "Save": "Сохранить",
    "Delete": "Удалить",
    "Edit": "Редактировать",
    "Share": "Поделиться",
    "Generate": "Распечатать",
    "SignIn": "Войти",
    "SignOut": "Выход",
    "YouWillBeSignedOut": "Вы выйдете из системы",
    "SignUp": "Зарегистрироваться",
    "SearchAddress": "Искать по адресу",
    "Title": "Название",
    "Unknown": "Неизвестный",
    "Price": "Цена",
    "Venue": "Место проведения",
    "Address": "Адрес",
    "Dates": "Даты",
    "Time": "Время",
    "Styles": "Стили",
    "Type": "Тип",
    "NewUser": "Новый пользователь",
    "Username": "Имя пользователя",
    "Password": "Пароль",
    "NewPassword": "Новый пароль",
    "Email": "Эл. адрес",
    "Saving": "Сохранение...",
    "SavingWine": "Сохранение вина...",
    "CommunicationWithTheServer": "Идет связь с сервером...",
    "Loading": "Загрузка данных...",
    "Deleting": "Удаление...",
    "UserSettings": "Пользовательские настройки",
    "UserSettingsSaved": "Пользовательские настройки сохранены",
    "UserSettingsNotSaved": "Не удалось сохранить настройки пользователя",
    "Sugar": "Сахар",
    "Salt": "Соль",
    "Fat": "Жир",
    "Spiciness": "Пряность",
    "Acidity": "Кислотность",
    "Astringency": "Терпкость",
    "Tannins": "Танины",
    "Body": "Тело",
    "Bitterness": "Горечь",
    "Persistence": "Стойкость",
    "Complexity": "Комплексность",
    "Gas": "Газ",
    "Description": "Описание",
    "Label": "Этикетка",
    "Visual": "Внешний вид",
    "Olfaction": "Обоняние",
    "Taste": "Вкус",
    "Conclusion": "Заключение",
    "Name": "Название",
    "TastingDate": "Дата дегустации",
    "Vintage": "Миллезим",
    "Alcohol": "Алкоголь",
    "Organic": "Органический",
    "Sulfites": "Сульфиты",
    "Appellation": "Аппеллясьон",
    "Producer": "Производитель",
    "Boutique": "Бутик",
    "Varieties": "Сорты",
    "Intensity": "Интенсивность ароматов",
    "PickAromas": "Выбрать ароматы",
    "BackToWineEdit": "Вернуться к редактированию вина",
    "Aromas": "Ароматы",
    "Comments": "Комментарии",
    "ShowHideSelectedAromas": "показать/скрыть выбранные ароматы",
    "ShowHideFilters": "показать/скрыть фильтры",
    "TapToSelectAromas": "Нажмите, чтобы выбрать ароматы",
    "TapToSelectFood": "Нажмите, чтобы выбрать еду",
    "AcidityFlat": "Плоский",
    "AcidityNone": "Никто",
    "AcidityLow": "Низкий",
    "AcidityMedium": "Средний",
    "AcidityHigh": "Высокая кислотность",
    "AcidityFresh": "Свежее",
    "AcidityAcid": "Кислый",
    "AstringencyNone": "Без",
    "AstringencyLow": "Низкая",
    "AstringencyMedium": "Средняя",
    "AstringencyTannic": "Терпкое",
    "AstringencyRough": "Грубое",
    "IntensityLow": "Низкая",
    "IntensityMediumLow": "Средне-низкая",
    "IntensityMedium": "Средняя",
    "IntensityMediumHigh": "Средне-высокая",
    "IntensityHigh": "Высокая",
    "FatNone": "Без",
    "FatLow": "Низкая",
    "FatMedium": "Средняя",
    "FatFat": "Жирная",
    "BodyFluid": "Жидкое",
    "BodyLight": "Свет",
    "BodyMedium": "Середина",
    "BodyFull": "Полный",
    "BodyHeavy": "Тяжелый",
    "PersistenceNone": "Никто",
    "PersistenceShort": "короткий",
    "PersistenceMedium": "Середина",
    "PersistenceLong": "Длинная",
    "PersistenceExtra": "Дополнительный",
    "TanninsNone": "Никто",
    "TanninsLight": "Свет",
    "TanninsSmooth": "Гладкий",
    "TanninsDry": "Сухой",
    "TanninsHarsh": "Жесткий",
    "TransparencyTransparent": "Прозрачный",
    "TransparencyTinted": "Тонированный",
    "TransparencyMedium": "Середина",
    "TransparencyHue": "оттенок",
    "TransparencyOpaque": "Непрозрачное",
    "SugarExtraBrut": "Экстра брют",
    "SugarBrut": "Брют",
    "SugarDry": "Полусухое",
    "SugarNone": "Сухое",
    "SugarLow": "Низкий уровень сахара",
    "SugarSemiDry": "Полусладкое",
    "SugarSweet": "Сладкое",
    "SugarVerySweet": "Очень сладкое",
    "SugarLiquor": "Ликёрное",
    "SpicinessNone": "Без",
    "SpicinessLow": "Немного",
    "SpicinessSpicy": "Острое",
    "SpicinessHot": "Жгущее",
    "SaltNone": "Без",
    "SaltSalty": "Соленое",
    "SaltVerySalty": "Очень соленое",
    "SaltMineral": "Минеральное",
    "SaltSaline": "Соленое",
    "ParticlesLimpid": "Прозрачное",
    "ParticlesPresent": "Настоящее время",
    "ParticlesCloudy": "Облачно",
    "GasStill": "Еще",
    "GasBeady": "Бусинка",
    "GasSemiSparkling": "полуигристое",
    "GasSparkling": "игристое",
    "BitternessNone": "Никто",
    "BitternessBitterish": "Горьковатый",
    "BitternessBitter": "Горький",
    "BioNo": "Нет",
    "BioOrganic": "Органический",
    "BioBiodynamic": "Биодинамический",
    "BioEnvironment": "Экологичность",
    "SulfitesYes": "Добавлены сульфиты",
    "SulfitesNo": "Без добавления сульфитов",
    "WineNotSaved": "Не удалось сохранить вино",
    "WineSaved": "Ваше вино было сохранено",
    "FoodNotSaved": "Не удалось сохранить пост о еде",
    "FoodSaved": "Ваш пост о еде сохранен",
    "WineDeleted": "Ваше вино было удалено",
    "IncompleteInformation": "Неполная информация",
    "EmptyWineName": "Отсутствует название вина",
    "EmptyWineLabel": "Этикетка не указана",
    "EmptyFoodImage": "Фото не предоставлено",
    "EmptyVintage": "Отсутствует миллезим",
    "EmptyTastingDate": "Отсутствует дата дегустации",
    "EmptyAlcohol": "Отсутствует градус алкоголя",
    "EmptyAppellation": "Отсутствует аппеллясьон",
    "AppellationWillBeCreated": "(аппеллясьон) будет создан",
    "EmptyProducer": "Отсутствует производитель",
    "ProducerWillBeCreated": "(производитель) будет создан",
    "EmptyBoutique": "Отсутствует бутик",
    "BoutiqueWillBeCreated": "(бутик) будет создан",
    "EmptyVarieties": "Отсутствует список сортов",
    "EmptyAromas": "Отсутствует список ароматов",
    "EmptyWines": "Отсутствует список вин",
    "Wines": "вина",
    "Tags": "Теги",
    "EmptyTags": "Теги еды не выбраны",
    "EmptyIntensity": "Неопределенная интенсивность",
    "EmptyColor": "Неопределенный цвет",
    "Color": "Цвет",
    "Theme": "Тема",
    "NodeAskPermission": "Попросите стать модератором или сообщить о проблеме",
    "WillBeDeleted": "будет удален!",
    "Ok": "Ok",
    "Confirm": "Подтверждать",
    "Cancel": "Отмена",
    "UserNotFound": "не найден или неверный пароль",
    "UseTaken": "Имя пользователя уже занято",
    "MailTaken": "адрес уже занят",
    "PasswordReset": "Сброс пароля",
    "UnableToConnect": "Не удается подключиться к серверу",
    "GeolocationFailed": "Геолокация не удалась",
    "GeolocationDisabled": "Геолокация отключена",
    "DefineAsDefaultLocation": "Нажмите здесь, чтобы определить это местоположение по умолчанию",
    "Today": "Сегодня",
    "LoginToPostMessages": "Пожалуйста, войдите или зарегистрируйтесь, чтобы отправлять сообщения. Это займет меньше одной минуты",
    "UnableToPostMessages": "Невозможно опубликовать ваше сообщение, <br> пожалуйста, подтвердите свою сеть",
    "CommentViolation": "Ваш комментарий нарушает наши правила",
    "ServerGetResultsError": "Не удалось подключиться к серверу, <br> повторите попытку позже",
    "UploadTimeout": "Загрузка изображения заняла слишком много времени. Пожалуйста, проверьте состояние сети и повторите попытку.",
    "UploadError": "Не удалось загрузить изображение. Проверьте состояние сети и повторите попытку.",
    "FromDate": "От",
    "TillDate": "до",
    "InvalidDates": "Неверный формат даты",
    "InvalidPlace": "Недопустимое место",
    "GettingUserPosition": "Инициализация карты",
    "PermissionsNeeded": "Необходимы разрешения",
    "MapPermission": "Разрешите доступ к местоположению, чтобы показать ближайшие винные магазины",
    "TranslationQuotaExceeded": "К сожалению, ваша квота на перевод <br> в день превышена",
    "OneMoment": "Настройка приложения, пожалуйста, подождите...",
    "Connecting": "Подключение...",
    "YouAreOffline": "Ты не в сети",
    "InitializationError": "Не удалось инициализировать приложение<br>Пожалуйста, проверьте подключение к Интернету<br>Или повторите попытку позже",
    "AccessLocation": "Разрешить местоположение",
    "GoToSettings": "Зайдите в настройки телефона",
    "AllowLocation": "Разрешить местоположению показывать вина возле вас",
    "ShowFullArticle": "Показать всю статью",
    "SearchResults": "Результаты поиска",
    "SearchOnline": "Поиск онлайн",
    "SearchMoreOnline": "Искать больше онлайн",
    "NoRecordsFound": "Записей не найдено",
    "NoResultsFoundFor": "Не найдено результатов по",
    "YouWillBeLoggedOut": "Вы выйдете из системы",
    "Poor": "Плохой",
    "Mediocre": "Посредственный",
    "Average": "Средний",
    "Good": "Хороший",
    "Excellent": "Превосходный",
    "YouVoted": "Вы проголосовали",
    "Level": "Уровень",
    "Votes": "Голоса",
    "PleaseRateUsTitle": "Оцените приложение!",
    "PleaseRateUsContent": "Эта услуга совершенно бесплатна и без рекламы, но чтобы донести ее до вас, требуется много времени и усилий. Пожалуйста, оцените приложение в магазине",
    "AlreadyDone": "Уже сделано!",
    "ThankYou": "Спасибо!",
    "UploadingLabel": "Загрузка ярлыка..",
    "UploadingImage": "Загрузка изображения..",
    "Done": "Сделанный!",
    "Skip": "Пропускать",
    "About": "О",
    "Welcome": "Добро пожаловать в Винтуозо!",
    "MyCellar": "Мой винный погреб",
    "Access": "Доступ",
    "Navigation": "Навигация",
    "SearchFor": "Поиск",
    "FoodPairing": "Сочетания блюд",
    "Profile": "Профиль",
    "Natural": "Натуральное",
    "OnlyNaturalWines": "Только натуральные вина",
    "OnlyBioWines": "Только органические вина",
    "OnlyVeganWines": "Только веганские вина",
    "Vegan": "Веган",
    "VeganNo": "Не веган",
    "VeganYes": "Веган",
    "Stock": "Колличество",
    "OpenANewBottle": "Открыть новую бутылку",
    "PostAComment": "Оставить комментарий",
    "Post": "Отправить",
    "DarkMode": "Темный режим",
    "NotABottle": "На фото не бутылка вина, пожалуйста, предоставьте другое фото",
    "ExplicitContent": "Обнаружен нецензурный контент!",
    "ProcessingImage": "Обработка изображения, подождите.."
}